modelbest_sdk/__init__.py
modelbest_sdk/git_info.txt
modelbest_sdk/dataset/__init__.py
modelbest_sdk/dataset/batched_dataset.py
modelbest_sdk/dataset/constant.py
modelbest_sdk/dataset/modelbest_dataloader.py
modelbest_sdk/dataset/prefetch_chunk_dataset.py
modelbest_sdk/dataset/segment_dataset.py
modelbest_sdk/dataset/weighted_dataset.py
modelbest_sdk/dataset/batch_packer/__init__.py
modelbest_sdk/dataset/batch_packer/audio_batch_packer.py
modelbest_sdk/dataset/batch_packer/batch_packer.py
modelbest_sdk/dataset/batch_packer/batch_packer_factory.py
modelbest_sdk/dataset/batch_packer/cpm_flash_attn_batch_packer.py
modelbest_sdk/dataset/batch_packer/megatron_batch_packer.py
modelbest_sdk/dataset/batch_packer/mmseq_batch_packer.py
modelbest_sdk/dataset/common/__init__.py
modelbest_sdk/dataset/common/cache.py
modelbest_sdk/dataset/common/range.py
modelbest_sdk/dataset/sampler/__init__.py
modelbest_sdk/dataset/sampler/sampler.py
modelbest_sdk/dataset/sampler/sampler_factory.py
modelbest_sdk/dataset/sampler/weighted_megatron_sampler.py
modelbest_sdk/dataset/sampler/weighted_sampler.py
modelbest_sdk/dataset/segment/__init__.py
modelbest_sdk/dataset/segment/conditionl_fixed_length_segment.py
modelbest_sdk/dataset/segment/fixed_length_segment.py
modelbest_sdk/dataset/segment/no_segment.py
modelbest_sdk/dataset/segment/rolling_truncate_segment.py
modelbest_sdk/dataset/segment/segment.py
modelbest_sdk/dataset/segment/segment_factory.py
modelbest_sdk/dataset/thrift_wrapper/__init__.py
modelbest_sdk/dataset/thrift_wrapper/base_doc.py
modelbest_sdk/dataset/thrift_wrapper/dataset_checkpoint.py
modelbest_sdk/dataset/thrift_wrapper/dataset_context.py
modelbest_sdk/dataset/thrift_wrapper/messages.py
modelbest_sdk/dataset/thrift_wrapper/metadata.py
modelbest_sdk/dataset/thrift_wrapper/utils.py
modelbest_sdk/file_format/__init__.py
modelbest_sdk/file_format/mbtable.py
modelbest_sdk/file_format/mbtable_builder.py
modelbest_sdk/file_format/mbtable_partition.py
modelbest_sdk-0.3.1.dist-info/METADATA
modelbest_sdk-0.3.1.dist-info/WHEEL
modelbest_sdk-0.3.1.dist-info/top_level.txt
modelbest_sdk-0.3.1.dist-info/RECORD
