Metadata-Version: 2.1
Name: modelbest-sdk
Version: 0.3.1
Summary: Everything about modelbest data include data format mbtable, dataset, dataloader, and tools
Home-page: https://codeup.aliyun.com/64ddb0a87f62ff9b3d23ca15/modelbest_sdk
Author: HankyZhao
Author-email: zhq980115@gmail.com
Classifier: Programming Language :: Python :: 3
Classifier: License :: OSI Approved :: MIT License
Classifier: Operating System :: OS Independent
Requires-Python: >=3.8
